qandaomr
